.coveragerc
.isort.cfg
.pylintrc
.style.yapf
LICENSE
MANIFEST.in
Makefile
README.md
mypy.ini
setup.py
cloudie/__init__.py
cloudie/__main__.py
cloudie/cli.py
cloudie/compute.py
cloudie/config.py
cloudie/group.py
cloudie/option.py
cloudie/security.py
cloudie/table.py
cloudie/utils.py
cloudie.egg-info/PKG-INFO
cloudie.egg-info/SOURCES.txt
cloudie.egg-info/dependency_links.txt
cloudie.egg-info/entry_points.txt
cloudie.egg-info/requires.txt
cloudie.egg-info/top_level.txt
requirements/README.md
requirements/requirements-dev-1.txt
requirements/requirements-dev-2.txt
requirements/requirements-dev-3.txt
requirements/requirements.txt
tests/__init__.py
tests/helpers.py
tests/test_cli.py
tests/test_compute.py
tests/test_config.py
tests/test_group.py
tests/test_option.py
tests/test_security.py
tests/test_table.py
tests/test_utils.py