Metadata-Version: 1.0
Name: cloudie
Version: 0.1.1
Summary: Command-line interface for various cloud services
Home-page: https://github.com/dyntopia/cloudie
Author: Hans Jerry Illikainen
Author-email: hji@dyntopia.com
License: BSD-2-Clause
Platform: UNKNOWN
